[
  {
    "id": "fish_ro",
    "name": "Cá rô",
    "rarity": "Common",
    "baseChance": 100,
    "value": 10,
    "xp": 5,
    "minSize": 10,
    "maxSize": 30,
    "biomes": ["river"]
  },
  {
    "id": "carp",
    "name": "Cá chép",
    "rarity": "Common",
    "baseChance": 70,
    "value": 15,
    "xp": 6,
    "minSize": 15,
    "maxSize": 45,
    "biomes": ["river", "lake"]
  },
  {
    "id": "tilapia",
    "name": "Cá rô phi",
    "rarity": "Common",
    "baseChance": 55,
    "value": 18,
    "xp": 8,
    "minSize": 20,
    "maxSize": 50,
    "biomes": ["river", "lake"]
  },
  {
    "id": "catfish",
    "name": "Cá trê",
    "rarity": "Common",
    "baseChance": 40,
    "value": 25,
    "xp": 10,
    "minSize": 20,
    "maxSize": 70,
    "biomes": ["river", "swamp"]
  },
  {
    "id": "eel",
    "name": "Lươn",
    "rarity": "Rare",
    "baseChance": 12,
    "value": 80,
    "xp": 25,
    "minSize": 40,
    "maxSize": 120,
    "biomes": ["swamp", "river"]
  },
  {
    "id": "salmon",
    "name": "Cá hồi",
    "rarity": "Rare",
    "baseChance": 10,
    "value": 100,
    "xp": 35,
    "minSize": 30,
    "maxSize": 90,
    "biomes": ["river", "ocean"]
  },

  {
    "id": "golden_koi",
    "name": "Cá koi vàng",
    "rarity": "Epic",
    "baseChance": 2,
    "value": 800,
    "xp": 180,
    "minSize": 50,
    "maxSize": 120,
    "biomes": ["lake"]
  },
  {
    "id": "piranha",
    "name": "Cá piranha",
    "rarity": "Rare",
    "baseChance": 18,
    "value": 120,
    "xp": 40,
    "minSize": 20,
    "maxSize": 60,
    "biomes": ["lake"]
  },
  {
    "id": "sturgeon",
    "name": "Cá tầm",
    "rarity": "Epic",
    "baseChance": 3,
    "value": 950,
    "xp": 220,
    "minSize": 80,
    "maxSize": 250,
    "biomes": ["lake"]
  },

  {
    "id": "electric_eel",
    "name": "Lươn điện",
    "rarity": "Epic",
    "baseChance": 1.5,
    "value": 1400,
    "xp": 300,
    "minSize": 80,
    "maxSize": 200,
    "biomes": ["swamp"]
  },
  {
    "id": "crocodile",
    "name": "Cá sấu",
    "rarity": "Legendary",
    "baseChance": 0.5,
    "value": 3000,
    "xp": 1000,
    "minSize": 1000,
    "maxSize": 3000,
    "biomes": ["swamp"]
  },
  {
    "id": "gar",
    "name": "Cá sấu hỏa tiễn",
    "rarity": "Legendary",
    "baseChance": 0.2,
    "value": 4000,
    "xp": 1500,
    "minSize": 1000,
    "maxSize": 2600,
    "biomes": ["swamp"]
  },

  {
    "id": "tuna",
    "name": "Cá ngừ",
    "rarity": "Rare",
    "baseChance": 8,
    "value": 140,
    "xp": 50,
    "minSize": 70,
    "maxSize": 200,
    "biomes": ["ocean"]
  },
  {
    "id": "octopus",
    "name": "Bạch tuộc",
    "rarity": "Rare",
    "baseChance": 5,
    "value": 220,
    "xp": 70,
    "minSize": 40,
    "maxSize": 150,
    "biomes": ["ocean", "deep_ocean"]
  },
  {
    "id": "swordfish",
    "name": "Cá kiếm",
    "rarity": "Epic",
    "baseChance": 3,
    "value": 1000,
    "xp": 220,
    "minSize": 100,
    "maxSize": 300,
    "biomes": ["ocean"]
  },
  {
    "id": "shark",
    "name": "Cá mập",
    "rarity": "Legendary",
    "baseChance": 0.5,
    "value": 7000,
    "xp": 1000,
    "minSize": 200,
    "maxSize": 700,
    "biomes": ["ocean"]
  },
  {
    "id": "hammerhead",
    "name": "Cá mập đầu búa",
    "rarity": "Legendary",
    "baseChance": 0.3,
    "value": 12000,
    "xp": 1800,
    "minSize": 300,
    "maxSize": 900,
    "biomes": ["ocean"]
  },

  {
    "id": "giant_squid",
    "name": "Mực khổng lồ",
    "rarity": "Epic",
    "baseChance": 1,
    "value": 2500,
    "xp": 450,
    "minSize": 200,
    "maxSize": 500,
    "biomes": ["deep_ocean"]
  },
  {
    "id": "sea_serpent",
    "name": "Rắn biển",
    "rarity": "Legendary",
    "baseChance": 0.15,
    "value": 25000,
    "xp": 3000,
    "minSize": 400,
    "maxSize": 1200,
    "biomes": ["deep_ocean"]
  },
  {
    "id": "leviathan",
    "name": "Leviathan",
    "rarity": "Mythic",
    "baseChance": 0.03,
    "value": 150000,
    "xp": 15000,
    "minSize": 500,
    "maxSize": 1500,
    "biomes": ["deep_ocean"]
  },
  {
    "id": "kraken",
    "name": "Kraken",
    "rarity": "Mythic",
    "baseChance": 0.01,
    "value": 300000,
    "xp": 30000,
    "minSize": 1000,
    "maxSize": 3000,
    "biomes": ["deep_ocean"]
  },

  {
    "id": "lava_carp",
    "name": "Cá dung nham",
    "rarity": "Common",
    "baseChance": 50,
    "value": 80,
    "xp": 30,
    "minSize": 20,
    "maxSize": 60,
    "biomes": ["lava"]
  },
  {
    "id": "magma_eel",
    "name": "Lươn magma",
    "rarity": "Rare",
    "baseChance": 8,
    "value": 400,
    "xp": 120,
    "minSize": 50,
    "maxSize": 150,
    "biomes": ["lava"]
  },
  {
    "id": "inferno_shark",
    "name": "Cá mập địa ngục",
    "rarity": "Epic",
    "baseChance": 1.5,
    "value": 5000,
    "xp": 800,
    "minSize": 200,
    "maxSize": 500,
    "biomes": ["lava"]
  },
  {
    "id": "phoenix_fish",
    "name": "Cá phượng hoàng",
    "rarity": "Legendary",
    "baseChance": 0.08,
    "value": 60000,
    "xp": 8000,
    "minSize": 100,
    "maxSize": 300,
    "biomes": ["lava"]
  },
  {
    "id": "lava_devil",
    "name": "Cá quỷ dung nham",
    "rarity": "Legendary",
    "baseChance": 0.04,
    "value": 85000,
    "xp": 10000,
    "minSize": 250,
    "maxSize": 700,
    "biomes": ["lava"]
  },

  {
    "id": "sky_ray",
    "name": "Cá đuối trời",
    "rarity": "Rare",
    "baseChance": 6,
    "value": 500,
    "xp": 180,
    "minSize": 100,
    "maxSize": 400,
    "biomes": ["sky"]
  },
  {
    "id": "cloud_serpent",
    "name": "Rắn mây",
    "rarity": "Epic",
    "baseChance": 1.2,
    "value": 6000,
    "xp": 1200,
    "minSize": 200,
    "maxSize": 700,
    "biomes": ["sky"]
  },
  {
    "id": "dragon_fish",
    "name": "Long Ngư",
    "rarity": "Mythic",
    "baseChance": 0.008,
    "value": 500000,
    "xp": 50000,
    "minSize": 200,
    "maxSize": 800,
    "biomes": ["sky"]
  },
  {
    "id": "angel_fish_sky",
    "name": "Cá thiên thần",
    "rarity": "Rare",
    "baseChance": 4,
    "value": 1200,
    "xp": 300,
    "minSize": 80,
    "maxSize": 250,
    "biomes": ["sky"]
  },
  {
    "id": "heaven_bird_fish",
    "name": "Cá chim thiên giới",
    "rarity": "Legendary",
    "baseChance": 0.05,
    "value": 100000,
    "xp": 15000,
    "minSize": 150,
    "maxSize": 500,
    "biomes": ["sky"]
  },

  {
    "id": "void_jelly",
    "name": "Sứa hư không",
    "rarity": "Epic",
    "baseChance": 0.5,
    "value": 12000,
    "xp": 3000,
    "minSize": 100,
    "maxSize": 500,
    "biomes": ["void"]
  },
  {
    "id": "abyss_eye",
    "name": "Nhãn cầu vực thẳm",
    "rarity": "Legendary",
    "baseChance": 0.08,
    "value": 80000,
    "xp": 12000,
    "minSize": 50,
    "maxSize": 200,
    "biomes": ["void"]
  },
  {
    "id": "void_whale",
    "name": "Cá voi hư không",
    "rarity": "Mythic",
    "baseChance": 0.001,
    "value": 2000000,
    "xp": 200000,
    "minSize": 5000,
    "maxSize": 12000,
    "biomes": ["void"]
  },
  {
    "id": "shadow_fish",
    "name": "Cá bóng tối",
    "rarity": "Rare",
    "baseChance": 2,
    "value": 4000,
    "xp": 1000,
    "minSize": 100,
    "maxSize": 350,
    "biomes": ["void"]
  },
  {
    "id": "void_hydra",
    "name": "Hydra hư không",
    "rarity": "Legendary",
    "baseChance": 0.01,
    "value": 500000,
    "xp": 60000,
    "minSize": 1000,
    "maxSize": 5000,
    "biomes": ["void"]
  }
]